parlant/adapters/db/json_file.py
parlant/adapters/db/mongo_db.py
parlant/adapters/db/transient.py
parlant/adapters/loggers/websocket.py
parlant/adapters/nlp/anthropic_service.py
parlant/adapters/nlp/aws_service.py
parlant/adapters/nlp/azure_service.py
parlant/adapters/nlp/cerebras_service.py
parlant/adapters/nlp/common.py
parlant/adapters/nlp/deepseek_service.py
parlant/adapters/nlp/gemini_service.py
parlant/adapters/nlp/hugging_face.py
parlant/adapters/nlp/lakera.py
parlant/adapters/nlp/litellm_service.py
parlant/adapters/nlp/ollama_service.py
parlant/adapters/nlp/openai_service.py
parlant/adapters/nlp/together_service.py
parlant/adapters/nlp/vertex_service.py
parlant/adapters/vector_db/chroma.py
parlant/adapters/vector_db/transient.py
parlant/api/agents.py
parlant/api/app.py
parlant/api/authorization.py
parlant/api/canned_responses.py
parlant/api/capabilities.py
parlant/api/chat/.gitignore
parlant/api/chat/.prettierrc
parlant/api/chat/.vite/deps_temp_0491001f/package.json
parlant/api/chat/components.json
parlant/api/chat/dist/app-logo.svg
parlant/api/chat/dist/assets/index-C3OsA0au.css
parlant/api/chat/dist/assets/index-p5Hb4rEe.js
parlant/api/chat/dist/assets/manifest-BRNJYplA.webmanifest
parlant/api/chat/dist/buttons/new-session-hover.svg
parlant/api/chat/dist/buttons/new-session.svg
parlant/api/chat/dist/emcie-placeholder.svg
parlant/api/chat/dist/empty-state.svg
parlant/api/chat/dist/favicon.svg
parlant/api/chat/dist/fonts/Inter/inter.css
parlant/api/chat/dist/fonts/Inter/static/Inter_28pt-Bold.ttf
parlant/api/chat/dist/fonts/Inter/static/Inter_28pt-ExtraBold.ttf
parlant/api/chat/dist/fonts/Inter/static/Inter_28pt-ExtraLight.ttf
parlant/api/chat/dist/fonts/Inter/static/Inter_28pt-Italic.ttf
parlant/api/chat/dist/fonts/Inter/static/Inter_28pt-Light.ttf
parlant/api/chat/dist/fonts/Inter/static/Inter_28pt-Medium.ttf
parlant/api/chat/dist/fonts/Inter/static/Inter_28pt-Regular.ttf
parlant/api/chat/dist/fonts/Inter/static/Inter_28pt-SemiBold.ttf
parlant-3.0.3.dist-info/METADATA
parlant-3.0.3.dist-info/WHEEL
parlant-3.0.3.dist-info/entry_points.txt
parlant-3.0.3.dist-info/licenses/LICENSE
parlant-3.0.3.dist-info/RECORD
