Metadata-Version: 2.4
Name: parlant
Version: 3.0.3
Summary: 
License: Apache-2.0
License-File: LICENSE
Author: Yam Marcovitz
Author-email: yam@emcie.co
Requires-Python: >=3.10,<4.0
Classifier: License :: OSI Approved :: Apache Software License
Classifier: Programming Language :: Python :: 3
Classifier: Programming Language :: Python :: 3.10
Classifier: Programming Language :: Python :: 3.11
Classifier: Programming Language :: Python :: 3.12
Classifier: Programming Language :: Python :: 3.13
Classifier: Programming Language :: Python :: 3.14
Provides-Extra: anthropic
Provides-Extra: aws
Provides-Extra: cerebras
Provides-Extra: chroma
Provides-Extra: deepseek
Provides-Extra: gemini
Provides-Extra: litellm
Provides-Extra: mongo
Provides-Extra: ollama
Provides-Extra: together
Provides-Extra: vertex
Requires-Dist: aiofiles (>=24.1.0,<25.0.0)
Requires-Dist: aiopenapi3 (==0.8.1)
Requires-Dist: aiorwlock (>=1.5.0,<2.0.0)
Requires-Dist: anthropic (>=0.60.0,<0.61.0) ; extra == "anthropic" or extra == "aws" or extra == "vertex"
Requires-Dist: authlib (>=1.6.5,<2.0.0)
Requires-Dist: boto3 (>=1.35.70,<2.0.0)
Requires-Dist: cachetools (==5.5.2)
Requires-Dist: cerebras-cloud-sdk (>=1.25.0,<2.0.0) ; extra == "cerebras"
Requires-Dist: chromadb (>=1.1.1,<2.0.0) ; extra == "chroma"
Requires-Dist: click (>=8.1.7,<9.0.0)
Requires-Dist: colorama (>=0.4.6,<0.5.0)
Requires-Dist: coloredlogs (>=15.0.1,<16.0.0)
Requires-Dist: contextvars (>=2.4,<3.0)
Requires-Dist: croniter (>=5.0.1,<6.0.0)
Requires-Dist: fastapi (==0.115.12)
Requires-Dist: fastmcp (==2.12.5)
Requires-Dist: google-api-core (>=2.24.2,<3.0.0) ; extra == "gemini" or extra == "vertex"
Requires-Dist: google-auth (>=2.40.0,<3.0.0) ; extra == "vertex"
Requires-Dist: google-genai (>=1.29.0,<2.0.0) ; extra == "gemini" or extra == "vertex"
Requires-Dist: httpx (>=0.28.1,<0.29.0)
Requires-Dist: jinja2 (>=3.1.6,<4.0.0)
Requires-Dist: jsonfinder (>=0.4.2,<0.5.0)
Requires-Dist: jsonschema (>=4.23.0,<5.0.0)
Requires-Dist: lagom (>=2.6.0,<3.0.0)
Requires-Dist: limits (>=5.5.0,<6.0.0)
Requires-Dist: litellm (>=1.61.16,<2.0.0) ; extra == "litellm"
Requires-Dist: mcp[cli] (>=1.7.1,<2.0.0)
Requires-Dist: more-itertools (>=10.3.0)
Requires-Dist: nano-vectordb (>=0.0.4.3,<0.0.5.0)
Requires-Dist: nanoid (>=2.0.0,<3.0.0)
Requires-Dist: networkx[default] (>=3.3,<4.0)
Requires-Dist: ollama (>=0.5.0,<0.6.0) ; extra == "ollama"
Requires-Dist: openai (>=1.45.0,<2.0.0)
Requires-Dist: openapi3-parser (==1.1.21)
Requires-Dist: opentelemetry-exporter-otlp-proto-grpc (==1.37.0)
Requires-Dist: parlant-client (>=3.0.1,<4.0.0)
Requires-Dist: pymongo (>=4.11.1,<5.0.0) ; extra == "mongo"
Requires-Dist: python-dateutil (>=2.8.2,<3.0.0)
Requires-Dist: python-dotenv (>=1.0.1,<2.0.0)
Requires-Dist: requests (>=2.32.3,<3.0.0)
Requires-Dist: rich (>=13.7.1,<14.0.0)
Requires-Dist: semver (>=3.0.2,<4.0.0)
Requires-Dist: structlog (>=24.4.0,<25.0.0)
Requires-Dist: tabulate (>=0.9.0,<0.10.0)
Requires-Dist: tiktoken (>=0.8,<0.9)
Requires-Dist: together (>=1.2.12,<2.0.0) ; extra == "together"
Requires-Dist: tokenizers (>=0.20,<0.21)
Requires-Dist: toml (>=0.10.2,<0.11.0)
Requires-Dist: torch (>=2.6.0,<3.0.0) ; extra == "anthropic" or extra == "aws" or extra == "together" or extra == "cerebras" or extra == "deepseek" or extra == "gemini" or extra == "vertex" or extra == "litellm"
Requires-Dist: transformers (>=4.46.2,<5.0.0) ; extra == "anthropic" or extra == "aws" or extra == "together" or extra == "cerebras" or extra == "deepseek" or extra == "vertex" or extra == "litellm"
Requires-Dist: types-aiofiles (>=24.1.0.20240626,<25.0.0.0)
Requires-Dist: types-cachetools (>=6.0.0.20250525,<7.0.0.0)
Requires-Dist: types-croniter (>=4.0.0.20241030,<5.0.0.0)
Requires-Dist: types-jsonschema (>=4.22.0.20240610,<5.0.0.0)
Requires-Dist: uvicorn (>=0.38.0,<0.39.0)
